rl_bandits-0.1.0.dist-info/licenses/LICENSE
rlbandits/__init__.py
rlbandits/agents/__init__.py
rlbandits/agents/base_agent.py
rlbandits/agents/epsilon_greedy.py
rlbandits/agents/gradient_bandit.py
rlbandits/agents/ucb.py
rlbandits/core/__init__.py
rlbandits/core/eval.py
rlbandits/core/runner.py
rlbandits/core/utils.py
rlbandits/envs/__init__.py
rlbandits/envs/nonstationary_bandit.py
rlbandits/envs/stationary_bandit.py
rlbandits/experiments/__init__.py
rlbandits/experiments/yaml_runner.py
rl_bandits-0.1.0.dist-info/METADATA
rl_bandits-0.1.0.dist-info/WHEEL
rl_bandits-0.1.0.dist-info/top_level.txt
rl_bandits-0.1.0.dist-info/RECORD
