Metadata-Version: 2.4
Name: rl-bandits
Version: 0.1.0
Summary: A modular library for multi-armed bandit algorithms
Author-email: Meeran Malik <muhammadmeeran@gmail.com>
License-Expression: MIT
Project-URL: Homepage, https://github.com/meeran03/rl-bandits
Project-URL: Repository, https://github.com/meeran03/rl-bandits
Project-URL: Issues, https://github.com/meeran03/rl-bandits/issues
Classifier: Development Status :: 3 - Alpha
Classifier: Intended Audience :: Science/Research
Classifier: Programming Language :: Python :: 3
Classifier: Programming Language :: Python :: 3.9
Classifier: Programming Language :: Python :: 3.10
Classifier: Programming Language :: Python :: 3.11
Classifier: Programming Language :: Python :: 3.12
Classifier: Topic :: Scientific/Engineering :: Artificial Intelligence
Requires-Python: >=3.9
License-File: LICENSE
Requires-Dist: numpy>=1.20.0
Requires-Dist: matplotlib>=3.5.0
Requires-Dist: pyyaml>=6.0
Provides-Extra: dev
Requires-Dist: pytest>=7.0.0; extra == "dev"
Requires-Dist: pytest-cov>=4.0.0; extra == "dev"
Requires-Dist: black>=22.0.0; extra == "dev"
Requires-Dist: flake8>=5.0.0; extra == "dev"
Requires-Dist: mypy>=1.0.0; extra == "dev"
Requires-Dist: jupyter>=1.0.0; extra == "dev"
Requires-Dist: notebook>=6.4.0; extra == "dev"
Dynamic: license-file
